odoo/addons/hr_attendance_geolocation/README.rst
odoo/addons/hr_attendance_geolocation/__init__.py
odoo/addons/hr_attendance_geolocation/__manifest__.py
odoo/addons/hr_attendance_geolocation/data/location_data.xml
odoo/addons/hr_attendance_geolocation/i18n/hr_attendance_geolocation.pot
odoo/addons/hr_attendance_geolocation/models/__init__.py
odoo/addons/hr_attendance_geolocation/models/hr_attendance.py
odoo/addons/hr_attendance_geolocation/models/hr_employee.py
odoo/addons/hr_attendance_geolocation/readme/CONTRIBUTORS.rst
odoo/addons/hr_attendance_geolocation/readme/DESCRIPTION.rst
odoo/addons/hr_attendance_geolocation/static/description/icon.png
odoo/addons/hr_attendance_geolocation/static/description/index.html
odoo/addons/hr_attendance_geolocation/static/src/js/attendance_geolocation.js
odoo/addons/hr_attendance_geolocation/tests/__init__.py
odoo/addons/hr_attendance_geolocation/tests/test_hr_attendance_geolocation.py
odoo/addons/hr_attendance_geolocation/views/assets.xml
odoo/addons/hr_attendance_geolocation/views/hr_attendance_views.xml
odoo14_addon_hr_attendance_geolocation-14.0.2.0.0.dist-info/METADATA
odoo14_addon_hr_attendance_geolocation-14.0.2.0.0.dist-info/WHEEL
odoo14_addon_hr_attendance_geolocation-14.0.2.0.0.dist-info/top_level.txt
odoo14_addon_hr_attendance_geolocation-14.0.2.0.0.dist-info/RECORD
